{"meta":{"key":"ktmb","agency":"ktmb","category":null,"source":"https://api.data.gov.my/gtfs-static/ktmb","processedAt":"2026-07-20T17:51:07.285Z","agencyName":"Keretapi Tanah Melayu","feedInfo":null},"trips":[{"id":"ktmb:35","originalId":"35","routeId":"ktmb:SH","serviceId":"ktmb:intercity","headsign":null,"directionId":0,"shapeId":null},{"id":"ktmb:51","originalId":"51","routeId":"ktmb:SH","serviceId":"ktmb:intercity","headsign":null,"directionId":0,"shapeId":null},{"id":"ktmb:53","originalId":"53","routeId":"ktmb:SH","serviceId":"ktmb:intercity","headsign":null,"directionId":0,"shapeId":null},{"id":"ktmb:57","originalId":"57","routeId":"ktmb:SH","serviceId":"ktmb:intercity","headsign":null,"directionId":0,"shapeId":null},{"id":"ktmb:52","originalId":"52","routeId":"ktmb:SH","serviceId":"ktmb:intercity","headsign":null,"directionId":1,"shapeId":null},{"id":"ktmb:34","originalId":"34","routeId":"ktmb:SH","serviceId":"ktmb:intercity","headsign":null,"directionId":1,"shapeId":null},{"id":"ktmb:58","originalId":"58","routeId":"ktmb:SH","serviceId":"ktmb:intercity","headsign":null,"directionId":1,"shapeId":null},{"id":"ktmb:60","originalId":"60","routeId":"ktmb:SH","serviceId":"ktmb:intercity","headsign":null,"directionId":1,"shapeId":null},{"id":"ktmb:27","originalId":"27","routeId":"ktmb:ERT","serviceId":"ktmb:intercity","headsign":null,"directionId":0,"shapeId":null},{"id":"ktmb:26","originalId":"26","routeId":"ktmb:ERT","serviceId":"ktmb:intercity","headsign":null,"directionId":1,"shapeId":null}],"stopTimes":[["ktmb:26","ktmb:68700","28:11:00","28:35:00",3700],["ktmb:26","ktmb:69600","28:52:00","28:52:00",4000],["ktmb:26","ktmb:76800","32:01:00","32:01:00",5900],["ktmb:27","ktmb:76800","24:57:00","24:57:00",3300],["ktmb:27","ktmb:69600","28:06:00","28:06:00",5200],["ktmb:27","ktmb:68700","28:24:00","28:25:00",5500],["ktmb:34","ktmb:68700","14:17:00","14:19:00",1700],["ktmb:34","ktmb:69600","14:39:00","14:40:00",2000],["ktmb:35","ktmb:69600","12:37:00","12:38:00",400],["ktmb:35","ktmb:68700","12:58:00","13:00:00",700],["ktmb:51","ktmb:76800","09:18:00","09:18:00",3300],["ktmb:52","ktmb:76800","04:28:00","04:28:00",300],["ktmb:53","ktmb:76800","12:03:00","12:03:00",3300],["ktmb:57","ktmb:76800","22:00:00","22:00:00",3300],["ktmb:58","ktmb:76800","15:03:00","15:03:00",300],["ktmb:60","ktmb:76800","17:53:00","17:53:00",1700]],"calendars":[{"serviceId":"ktmb:intercity","weekdays":[1,1,1,1,1,1,1],"startDate":"20220115","endDate":"20260721"}],"calendarDates":[],"frequencies":[]}